keyringpy/__init__.py
keyringpy/keyring.py
keyringpy-0.0.1.dist-info/LICENSE.txt
keyringpy-0.0.1.dist-info/METADATA
keyringpy-0.0.1.dist-info/WHEEL
keyringpy-0.0.1.dist-info/top_level.txt
keyringpy-0.0.1.dist-info/RECORD
