Metadata-Version: 2.1
Name: keyringpy
Version: 0.0.1
Summary: Simple encryption-at-rest with key rotation support for Python.
Home-page: https://github.com/dannluciano/keyringpy
Author: Dann Luciano
Author-email: dannluciano@gmail.com
License: MIT
Platform: UNKNOWN
Classifier: License :: OSI Approved :: MIT License
Classifier: Programming Language :: Python
Classifier: Programming Language :: Python :: 3
Classifier: Programming Language :: Python :: 3.6
Classifier: Programming Language :: Python :: Implementation :: CPython
Classifier: Programming Language :: Python :: Implementation :: PyPy
Requires-Python: >=3.6.0
License-File: LICENSE.txt
Requires-Dist: pycryptodome
